cnnechart/__init__.py
cnnechart-0.1.0.dist-info/LICENSE
cnnechart-0.1.0.dist-info/METADATA
cnnechart-0.1.0.dist-info/WHEEL
cnnechart-0.1.0.dist-info/top_level.txt
cnnechart-0.1.0.dist-info/RECORD
